SEBAL_soil_heat_flux/SEBAL_soil_heat_flux.py
SEBAL_soil_heat_flux/__init__.py
SEBAL_soil_heat_flux/version.txt
sebal_soil_heat_flux-1.0.1.dist-info/licenses/LICENSE
sebal_soil_heat_flux-1.0.1.dist-info/METADATA
sebal_soil_heat_flux-1.0.1.dist-info/WHEEL
sebal_soil_heat_flux-1.0.1.dist-info/top_level.txt
sebal_soil_heat_flux-1.0.1.dist-info/RECORD
